[
  {
    "transactionId": "TXN1234567890",
    "tourId": "tour-saint-martin-001",
    "tourTitle": "Saint Martin",
    "tourImage": "https://i.ibb.co.com/7J23Bb3J/saintmartin.jpg",
    "pricePerPerson": 850,
    "numberOfTravelers": 2,
    "totalPrice": 1700,
    "customer": {
      "firstName": "John",
      "lastName": "Doe",
      "email": "john.doe@example.com",
      "phone": "+880 1700 123456"
    },
    "travelDate": "2025-06-15",
    "specialRequests": "Vegetarian meals preferred.",
    "bookingDate": "2025-04-21T10:32:00Z",
    "status": "Confirmed"
  },
  {
    "transactionId": "TXN0987654321",
    "tourId": "tour-bali-002",
    "tourTitle": "Bali",
    "tourImage": "https://i.ibb.co.com/7J23Bb3J/bali.jpg",
    "pricePerPerson": 1200,
    "numberOfTravelers": 1,
    "totalPrice": 1200,
    "customer": {
      "firstName": "Jane",
      "lastName": "Smith",
      "email": "jane.smith@example.com",
      "phone": "+880 1700 654321"
    },
    "travelDate": "2025-07-20",
    "specialRequests": "Window seat requested.",
    "bookingDate": "2025-04-22T11:45:00Z",
    "status": "Pending"
  }
]